{
  "tiles" : [ {
    "scaleFactors" : [ 32, 16, 8, 4, 2, 1 ],
    "width" : 1024,
    "height" : 1024
  } ],
  "protocol" : "http://iiif.io/api/image",
  "sizes" : [ {
    "width" : 45,
    "height" : 71
  }, {
    "width" : 89,
    "height" : 141
  }, {
    "width" : 177,
    "height" : 282
  }, {
    "width" : 353,
    "height" : 563
  }, {
    "width" : 705,
    "height" : 1125
  }, {
    "width" : 1410,
    "height" : 2250
  } ],
  "profile" : "http://iiif.io/api/image/2/level0.json",
  "width" : 1410,
  "@id" : "https://theadmontlibrary.github.io/The-Admont-Archive/images/SecretGarden10",
  "@context" : "http://iiif.io/api/image/2/context.json",
  "height" : 2250
}